financial_modeling_prep/__init__.py
financial_modeling_prep/bulk.py
financial_modeling_prep/charts.py
financial_modeling_prep/commodities.py
financial_modeling_prep/company_info.py
financial_modeling_prep/company_search.py
financial_modeling_prep/constituents.py
financial_modeling_prep/crypto.py
financial_modeling_prep/dividends.py
financial_modeling_prep/earnings.py
financial_modeling_prep/earnings_transcripts.py
financial_modeling_prep/economic_data.py
financial_modeling_prep/esg.py
financial_modeling_prep/etf_holdings.py
financial_modeling_prep/financial_statements.py
financial_modeling_prep/forex.py
financial_modeling_prep/fundraising.py
financial_modeling_prep/insider_trading.py
financial_modeling_prep/institutional_stock_ownership.py
financial_modeling_prep/ipo_calendar.py
financial_modeling_prep/market_performance.py
financial_modeling_prep/mergers_and_acquisitions.py
financial_modeling_prep/mutual_fund_holdings.py
financial_modeling_prep/news.py
financial_modeling_prep/price_targets.py
financial_modeling_prep/quote.py
financial_modeling_prep/sales_revenue_by_segments.py
financial_modeling_prep/sec_filings.py
financial_modeling_prep/senate.py
financial_modeling_prep/splits.py
financial_modeling_prep/statement_analysis.py
financial_modeling_prep/stock_list.py
financial_modeling_prep/technical_indicators.py
financial_modeling_prep/upgrades_downgrades.py
financial_modeling_prep/valuation.py
financial_modeling_prep/websockets.py
financial_modeling_prep_api-0.1.2.dist-info/METADATA
financial_modeling_prep_api-0.1.2.dist-info/WHEEL
financial_modeling_prep_api-0.1.2.dist-info/licenses/LICENSE
financial_modeling_prep_api-0.1.2.dist-info/RECORD
