Metadata-Version: 2.1
Name: financial-modeling-prep-api
Version: 0.1.2
Summary: Python wrapper for financialmodelingprep.com API
Project-URL: Homepage, https://github.com/BillSchumacher/financial-modeling-prep
Project-URL: Bug Tracker, https://github.com/BillSchumacher/financial-modeling-prep/issues
Author-email: Bill Schumacher <34168009+BillSchumacher@users.noreply.github.com>
License-Expression: MIT
License-File: LICENSE
Classifier: Development Status :: 4 - Beta
Classifier: Environment :: Web Environment
Classifier: License :: OSI Approved :: MIT License
Classifier: Operating System :: OS Independent
Classifier: Programming Language :: Python :: 3
Classifier: Programming Language :: Python :: 3 :: Only
Classifier: Programming Language :: Python :: 3.9
Classifier: Programming Language :: Python :: 3.10
Classifier: Programming Language :: Python :: 3.11
Classifier: Topic :: Internet :: WWW/HTTP
Requires-Python: >3.8
Requires-Dist: requests-cache
Requires-Dist: websocket-client
